[
  {
    "sceneId": "tutorial_intro",
    "title": "教学关：奇怪的谋杀？",
    "text": "早晨07:43，你在上班的途中接到紧急任务，在离你很近的街道疑似发生命案。你来到现场，地上一动不动地躺着一个人，身下是一滩红色的液体。围观的人越围越多，他们举着手机拍摄，小声讨论“是不是凶案”。",
    "choices": [
      "蹲下看清地上的人，试图叫醒他 （+2）",
      "挨个问围观者发生了什么，记下他们说的 （+1）",
      "先上报疑似谋杀快讯，等待警察到场 （-2）"
    ]
  },
  {
    "sceneId": "tutorial_follow_wakeup",
    "title": "教学关：核实路线",
    "text": "“先生！先生！”你蹲下用力拍打地上躺着人的后背，围观群众用异样的眼光看着你。时间一分一秒过去，围观的人已经将镜头移到你的身上，你必须尽快核实真相，舆论系统已经预警，事件热度正在快速攀升。",
    "choices": [
      "寻找物业查询监控，试图找到人倒下的时间 （+2）",
      "询问目击者发生了什么 （+1）",
      "通知舆论控制办公室，先封控所有相关视频和言论 （-2）"
    ]
  },
  {
    "sceneId": "tutorial_follow_witness",
    "title": "教学关：核实路线",
    "text": "围观者七嘴八舌：有人说听到争吵后有人倒地，便利店老板说红色液体未必是血，物业已经到场分隔人群。时间一分一秒过去，你必须尽快核实真相，舆论系统已经预警，事件热度正在快速攀升。",
    "choices": [
      "寻找物业查询监控，试图找到人倒下的时间 （+2）",
      "继续询问目击者，把细节问到一致 （+1）",
      "通知舆论控制办公室，先封控所有相关视频和言论 （-2）"
    ]
  },
  {
    "sceneId": "tutorial_follow_report",
    "title": "教学关：核实路线",
    "text": "“疑似谋杀”快讯被层层上报后被驳回，不确定信息不能直接发布。时间一分一秒过去，你必须尽快核实真相，舆论系统已经预警，事件热度正在快速攀升。",
    "choices": [
      "寻找物业查询监控，试图找到人倒下的时间 （+2）",
      "询问目击者发生了什么 （+1）",
      "通知舆论控制办公室，先封控所有相关视频和言论 （-2）"
    ]
  },
  {
    "sceneId": "tutorial_resolution",
    "title": "教学关：误会澄清",
    "text": "你正打算做些什么，警车终于到了，结果很快出来：地上的人是醉酒后睡着，红色液体只是翻倒的油漆。刚才还在喊“谋杀”的人慢慢散开，巷口一下安静下来。你抬头看见天边发亮，真正的大事还在前面等你。",
    "choices": [
      "走出巷口，去真正的火场 （+1）"
    ]
  },
  {
    "sceneId": "tutorial_ending",
    "title": "教学关：结案",
    "text": "你把一条条线索拼回去，发出澄清：这不是谋杀。评论区的火气慢慢下去，人群也开始散开。你收起本子，转身去赶下一场更大的火。",
    "choices": [
      "离开巷口，赶往山火现场 （+1）"
    ]
  },
  {
    "sceneId": "intro",
    "title": "序章：不确定的第一小时",
    "text": "你被派去报道加州山火，当你赶到北加州时，天还没亮，远处已经是一片红。收音机里一直在报“哪里要撤离、哪条路封了”，手机群里却在传“仓库爆炸”和“有人瞒报”。同一件事，街上一个说法，网上又一个说法。你知道接下来每走一步，都会决定这场大火在大家心里会变成什么样子。",
    "choices": [
      "先去简报现场，听完再回火线 （+2）",
      "先去找那条爆炸视频最早是谁发的 （+1）",
      "先沿撤离路线一路往前看 （+1）",
      "先去县应急中心门口守消息 （+2）"
    ]
  },
  {
    "sceneId": "social_desk",
    "title": "社媒溯源台",
    "text": "你把手机和电脑摊在折叠桌上，反复看同一段火球视频。每刷新一次，标题就换一个词，评论区也吵成一团。有人说这就是今晚拍的，有人说这是一年前旧视频。你盯着画面里的路灯和屋顶，你该怎么做？",
    "choices": [
      "去视频评论区找最早发帖的人 （+2）",
      "去平台搜索这条视频从哪来 （+1）",
      "先照着传闻写一条短消息发出去 （-2）",
      "去联系上传者朋友，试着拿到原视频 （+2）"
    ]
  },
  {
    "sceneId": "field_probe",
    "title": "前线快查",
    "text": "你跟着巡逻车一路往前，路牌都被烟熏得看不清。前面是排成长队的撤离车辆，后面是还在冒火的山坡。每到一个路口，你都要决定是继续追，还是停下来记下眼前这一幕。真相正在被你逐渐拼凑成型。",
    "choices": [
      "跟着巡逻车往山脚再走一段 （+2）",
      "跟着撤离大巴去下一个集合点 （+1）",
      "停在路边先拍最吓人的画面 （-1）"
    ]
  },
  {
    "sceneId": "briefing",
    "title": "官方简报与信息落差",
    "text": "天亮后，临时指挥点开了简报会。台上在念数字，台下的人却在说“不是这样的”。有人说通知太晚，有人说实际撤离的人更多。你站在人群边上，一边听台上，一边听台下，感觉像站在两条河中间。",
    "choices": [
      "站在白板前一条条抄下刚更新的数字 （+2）",
      "离开会场去找居民，把两边说法放一起看 （+1）",
      "抓一句最吓人的话当标题先写 （-1）"
    ]
  },
  {
    "sceneId": "route_choice",
    "title": "路线选择",
    "text": "你站在三岔路口，左边是避难所的车灯，右边是医院门口的白灯，前方是排队的物资车。每条路都有人在等消息。你只能先选一条路跑过去，把那里的故事先带回来。",
    "choices": [
      "去避难所，看看大家今晚怎么过 （+1）",
      "去医院，看看门口排队到底有多长 （+1）",
      "去物资点，看车队是不是堵住了 （+1）",
      "去记者提问区，听别人都在追问什么 （+1）"
    ]
  },
  {
    "sceneId": "shelter",
    "title": "避难所的多重叙述",
    "text": "避难所里人挤人，孩子哭声和电话铃混在一起。门口牌子写着“床位满了”，志愿者却说还能再挪几张折叠床。有人说东西够，有人说昨晚就开始缺。你夹在中间，想先弄清今晚谁能睡下、谁要继续等。",
    "choices": [
      "去登记台翻名册，看看床位到底够不够 （+2）",
      "去临时帐篷问带孩子和老人来的家庭 （+1）",
      "先拍吵起来的人群，马上写一段发出去 （-1）"
    ]
  },
  {
    "sceneId": "shelter_conflict",
    "title": "避难所：账本冲突",
    "text": "你把三张纸摊在桌上：登记名字、床位安排、领物资记录。看起来差不多，但每一张都差一点点。志愿者说是忙乱写错了，居民说是有人没拿到。你盯着这些小差别，知道它们会变成明天最吵的话题。",
    "choices": [
      "把名册、物资单和现场人数放在一起慢慢对 （+2）",
      "把缺的东西打电话报上去，并记下回话 （+1）",
      "先跟着一个家庭走一圈，写他们这一晚 （-1）"
    ]
  },
  {
    "sceneId": "hospital",
    "title": "医院里的风险提醒",
    "text": "医院门口排着长队，老人和孩子裹着外套坐在墙边。护士一遍遍叫号，家属拿着药袋来回跑。白板上写满“咳嗽、胸闷、喘不过气”。你在这里听到的每一句，都比网络上的传闻更重。",
    "choices": [
      "去问护士每一段时间等了多久 （+2）",
      "去找值班医生，当面问要怎么防护 （+1）",
      "先拍候诊区最挤的时候，先发再补充 （-1）"
    ]
  },
  {
    "sceneId": "hospital_triage",
    "title": "医院：分诊压力",
    "text": "分诊屏上的等待时间不停往上跳，走廊里咳嗽声也没断过。你一手拿着护士给的记录，一手看着外面的空气变化。两条线在几个时间点突然一起冲高。你得想清楚，是先把这个变化讲出去，还是再多跑一步确认。",
    "choices": [
      "把“谁先来、谁等最久”按时间排成一行 （+2）",
      "先发一条温和提醒，告诉大家先怎么做 （+1）",
      "挑最严重的一例，写成“医院快撑不住” （-2）"
    ]
  },
  {
    "sceneId": "logistics",
    "title": "物资调度与质疑",
    "text": "物资点边上停满卡车，司机靠着车门抽烟等消息。负责人指着地图说“马上到”，志愿者却说“我们已经等很久了”。对讲机里不停喊“绕路、再绕路”。你想知道，到底是谁在路上，谁还没出发。",
    "choices": [
      "去找车队负责人，把出发和到达时间抄下来 （+2）",
      "跟一位司机重走一遍路线 （+1）",
      "先写“物资不见了”，把消息顶到最前 （-2）"
    ]
  },
  {
    "sceneId": "logistics_checkpoint",
    "title": "物流点：关键路口",
    "text": "关键路口的电子牌一直在变字：封路、改道、只让应急车过。你拿到司机手写时间，又拿到车队记录，两边在一段时间里对不上。那十几分钟空白像一个洞，谁都在往里塞自己的说法。你得把这个洞补上。",
    "choices": [
      "把司机手表时间、路牌和到站时间一个个对 （+2）",
      "把每次绕路原因写下来，能确认的先圈出来 （+1）",
      "先发“补给崩了”的提醒消息 （-2）"
    ]
  },
  {
    "sceneId": "data_room",
    "title": "数据整合",
    "text": "你回到临时桌前，把地图、笔记和拍到的照片一张张铺开。每条线索都能对上几段，却总有几处接不上。你在纸上画出时间线，发现有个时间点几乎所有地方都变得更糟。这个夜晚开始像一段完整故事，只差最后几块拼图。",
    "choices": [
      "把今晚发生的事按时间一格一格排好 （+2）",
      "先把对不上的地方写成三问，拿去当面问人 （+1）",
      "把还没弄明白的地方先留白，再去下一站 （+0）",
      "先把时间线放出来，让看见的人来补线索 （+1）"
    ]
  },
  {
    "sceneId": "press_pool",
    "title": "联合采访池",
    "text": "记者提问区里一排排话筒举起来，问题一个接一个。有人问路什么时候开，有人问人到底撤走多少。你握着本子排在后面，心里已经想好要问哪三句。轮到你时，四周突然安静了一秒。",
    "choices": [
      "轮到你时连问三句：现在多少、什么时候更新、前后为什么不一样 （+2）",
      "追问他们下一次几点说清楚 （+1）",
      "怕被请出去，于是把最硬的问题吞回去 （-2）"
    ]
  },
  {
    "sceneId": "rumor_trace",
    "title": "传闻追踪",
    "text": "那条“仓库爆炸”的视频还在疯传。画面里有火球，也有模糊的招牌字，但看不出到底在哪。发视频的账号很快就删了，反而让更多人相信“这肯定是真的”。你把关键画面截下来，准备拿着它去现场一一对。",
    "choices": [
      "拿着视频去现场比楼和路，看看是不是同一个地方 （+2）",
      "顺着转发一层层找，看看是谁最先发 （+1）",
      "先去问官方一句，再决定要不要继续追视频 （+1）"
    ]
  },
  {
    "sceneId": "osint_lab",
    "title": "开源核查实验室",
    "text": "你盯着那几帧画面看了很久：路灯方向、屋顶边线、远处的山影。越看越觉得这段视频有拼接痕迹，但还差一锤定音。现在你可以继续埋头查，也可以先拿这些疑点去当面追问。",
    "choices": [
      "翻旧地图和街景，试着找出拍摄位置 （+2）",
      "反复听这段声音，找剪过的痕迹 （+1）",
      "先把半成品结论丢进群里试反应 （-1）"
    ]
  },
  {
    "sceneId": "official_response",
    "title": "官方回应",
    "text": "你打通了官方电话，对方只说“还在查”。另一边，已经有人把“爆炸”两个字做成了大标题。你把对方每个字都记下来，发现他们始终不肯给肯定说法。你知道这时候一句写重了，就会把整条线带偏。",
    "choices": [
      "把每一句话都写清楚：这句确定，那句还不确定 （+2）",
      "去要一份值班记录，把缺的那几分钟补上 （+1）",
      "先用“真的爆炸了吗？”当标题推送出去 （-2）"
    ]
  },
  {
    "sceneId": "community_hearings",
    "title": "社区证言",
    "text": "你坐在路边台阶上，把今天听到的话一条条重写。有人说“我亲眼看见”，有人说“我在群里看到”。同一句“有爆炸”，每个人讲出的时间和地点都不一样。你只能把这些话分开，留下能互相对上的那一部分。",
    "choices": [
      "把证言分成三堆：亲眼看到的、听别人说的、网上传的 （+2）",
      "把每个人说的时间写在纸上，找重合的那几段 （+1）",
      "先剪最激动的片段发出去吸引人 （-1）"
    ]
  },
  {
    "sceneId": "verification",
    "title": "交叉核实",
    "text": "跑了一整圈后，你终于把大部分事情对上了：哪几条路封了，哪些街区在撤离，医院和避难所也能互相印证。只有“仓库爆炸”这一句还悬着。你翻着本子，感觉只差一个旁证，这个夜晚就能收口。",
    "choices": [
      "先发“已确认”版本，把没确认的单独放旁边 （+1）",
      "把复杂情况硬写成一句肯定话 （-2）",
      "先把你怎么查的过程公开，再发主稿 （+2）"
    ]
  },
  {
    "sceneId": "rapid_update",
    "title": "快更压力线",
    "text": "主编连发三条消息催你：“别人已经发了，你还要多久？”你桌上有两份稿，一份慢但稳，一份快但有洞。发布键就在屏幕右上角，像在催你按下去。你得决定今晚是要快一点，还是要稳一点。",
    "choices": [
      "改成滚动更新稿，每一段都写上时间和来源 （+1）",
      "先停十分钟，回头把证据顺序重新排序一次 （+2）",
      "继续抢时间，争议留到发完再说 （-3）"
    ]
  },
  {
    "sceneId": "drafting",
    "title": "稿件结构",
    "text": "你开始写稿，第一段写了又删，删了又写。是先写火有多大，还是先写人该往哪走？你知道开头三行会决定大家是更慌，还是更清楚。",
    "choices": [
      "开头先写三句：现在知道什么、不知道什么、下一步去哪里 （+2）",
      "先告诉大家往哪走、怎么保护自己，再讲来龙去脉 （+1）",
      "先把大爆炸作为标题突出事件严重性，后面再慢慢补充说明 （-2）"
    ]
  },
  {
    "sceneId": "editorial_review",
    "title": "编辑台复核",
    "text": "你和编辑并排坐着，一句一句过稿。每改掉一个词语，报告逐渐完善。改到最后，你们盯着开头那一段脑海里想的是同一件事：我们在向读者传递什么信息。",
    "choices": [
      "和编辑一条条过稿，把每句都挂上来源 （+2）",
      "找同事试读，看哪段最容易看错就立刻改 （+1）",
      "抓紧时间发布让公众了解事件的来龙去脉 （-2）"
    ]
  },
  {
    "sceneId": "final_decision",
    "title": "发布前抉择",
    "text": "最后确认时，屋里只剩键盘声和风声。还有一条线索在路上，读者却已经在等。你手指停在“发布”上，脑子里闪过今晚遇到的每一张脸。按下去之后，这个故事就会跑进很多人的手机里。",
    "choices": [
      "等待线索的完善发完整版，并写清楚下次更新的事件 （+2）",
      "先发短版，再告诉大家几点补全 （+1）",
      "先推一个大标题，正文后面再补 （-2）"
    ]
  },
  {
    "sceneId": "ending_good",
    "title": "结局：可信与有用",
    "text": "你这篇稿子发出去后，评论区第一次安静下来。有人说“终于看懂了该往哪走”，也有人把你的信息转给家人。传闻还在，但声音小了很多。你没有写出最炸的标题，却把这个夜晚讲成了一个能被相信的故事。",
    "choices": []
  },
  {
    "sceneId": "ending_bad",
    "title": "结局：可信度不足",
    "text": "稿子发出去后，评论区很快开始追问：“这句话从哪来的？”你文里几处没说清的地方，被别人截出来当成结论继续传。你当然还能在下一次更新补救，但这一轮，故事已经被嘈杂声音抢走了。",
    "choices": []
  }
]
